{
    "version": "https://jsonfeed.org/version/1",
    "title": "NCU 小白",
    "subtitle": "心之所向，素履以往",
    "icon": "https://ncufresher.github.io/images/favicon.ico",
    "description": "数据科学，大数据技术",
    "home_page_url": "https://ncufresher.github.io",
    "items": [
        {
            "id": "https://ncufresher.github.io/2024/04/15/20240415-%E4%B8%A4%E7%A7%8D%E5%BC%80%E5%8F%91%E6%9E%B6%E6%9E%84/",
            "url": "https://ncufresher.github.io/2024/04/15/20240415-%E4%B8%A4%E7%A7%8D%E5%BC%80%E5%8F%91%E6%9E%B6%E6%9E%84/",
            "title": "两种开发架构",
            "date_published": "2024-04-14T16:00:00.000Z",
            "content_html": "<h1 id=\"开发架构\"><a class=\"anchor\" href=\"#开发架构\">#</a> 开发架构</h1>\n<p>在计算中所有的应用程序常常基于以下两种开发架构：</p>\n<ul>\n<li>\n<p>C/S 架构（Client-Server）：客户端 - 服务器架构，这里的客户端显著的特点是需要下载，即安装在本地的应用，当使用这些软件时，常常需要与后端服务器进行数据连接。</p>\n</li>\n<li>\n<p>B/S 架构（Brower-Server）：浏览器 - 服务器架构，像日常常见的 WEB 程序，网站等，都是通过浏览器与后端服务器连接。</p>\n</li>\n</ul>\n<p>C/S 架构由于将软件安装在本地，因此在访问和运行过程中会更加稳定，但如果软件太大是便会占用较多的本地空间，而 B/S 架构于是显得轻量，当然也可以通过云计算模式将将服务在云端进行。</p>\n<p>当从这两个基本开发框架出发去看其他应用开发的过程时，便就更加清楚每一步的作用。</p>\n<h1 id=\"举例\"><a class=\"anchor\" href=\"#举例\">#</a> 举例</h1>\n<p>在使用 Hexo+Github 搭建个人博客时，搜索到的大部分是教你每一步怎么做怎么做，只要无脑按部就班便就能完成了，但是为什么是这样？</p>\n<p><img data-src=\"C:%5CUsers%5C16897%5CAppData%5CRoaming%5CTypora%5Ctypora-user-images%5Cimage-20240415161759399.png\" alt=\"image-20240415161759399\" /></p>\n<p>而到搜索具体的搭建的原理时的资料却是少之又少，从 B/S 架构来理解便就清楚多了。</p>\n<p><img data-src=\"C:%5CUsers%5C16897%5CAppData%5CRoaming%5CTypora%5Ctypora-user-images%5Cimage-20240415162532381.png\" alt=\"image-20240415162532381\" /></p>\n<p>Hexo 是一个静态网页框架，而 Github 提供了一个文件托管平台的作用，git 工具可以帮助我们从本地管理 Github 仓库，于是我们在使用浏览器时访问的其实是 github 的文件仓库，然后在本地使用 hexo 工具进行网页的管理与博客内容的上传，最终在 github 得到内容的更新，于是不同的内容便展现在网页端。</p>\n",
            "tags": [
                "基础理解"
            ]
        },
        {
            "id": "https://ncufresher.github.io/2024/04/15/%E5%BC%80%E5%8F%91%E6%9E%B6%E6%9E%84/%E4%B8%A4%E7%A7%8D%E5%BC%80%E5%8F%91%E6%9E%B6%E6%9E%84/",
            "url": "https://ncufresher.github.io/2024/04/15/%E5%BC%80%E5%8F%91%E6%9E%B6%E6%9E%84/%E4%B8%A4%E7%A7%8D%E5%BC%80%E5%8F%91%E6%9E%B6%E6%9E%84/",
            "title": "两种开发架构",
            "date_published": "2024-04-14T16:00:00.000Z",
            "content_html": "<h1 id=\"开发架构\"><a class=\"anchor\" href=\"#开发架构\">#</a> 开发架构</h1>\n<p>在计算中所有的应用程序常常基于以下两种开发架构：</p>\n<ul>\n<li>\n<p>C/S 架构（Client-Server）：客户端 - 服务器架构，这里的客户端显著的特点是需要下载，即安装在本地的应用，当使用这些软件时，常常需要与后端服务器进行数据连接。</p>\n</li>\n<li>\n<p>B/S 架构（Brower-Server）：浏览器 - 服务器架构，像日常常见的 WEB 程序，网站等，都是通过浏览器与后端服务器连接。</p>\n</li>\n</ul>\n<p>C/S 架构由于将软件安装在本地，因此在访问和运行过程中会更加稳定，但如果软件太大是便会占用较多的本地空间，而 B/S 架构于是显得轻量，当然也可以通过云计算模式将将服务在云端进行。</p>\n<p>当从这两个基本开发框架出发去看其他应用开发的过程时，便就更加清楚每一步的作用。</p>\n<h1 id=\"举例\"><a class=\"anchor\" href=\"#举例\">#</a> 举例</h1>\n<p>在使用 Hexo+Github 搭建个人博客时，搜索到的大部分是教你每一步怎么做怎么做，只要无脑按部就班便就能完成了，但是为什么是这样？</p>\n<p><img data-src=\"/images/%E5%BC%80%E5%8F%91%E6%9E%B6%E6%9E%841.png\" alt=\"开发架构1\" /></p>\n<p>而到搜索具体的搭建的原理时的资料却是少之又少，从 B/S 架构来理解便就清楚多了。</p>\n<p><img data-src=\"/images/%E5%BC%80%E5%8F%91%E6%9E%B6%E6%9E%842.png\" alt=\"开发架构2\" /></p>\n<p>Hexo 是一个静态网页框架，而 Github 提供了一个文件托管平台的作用，git 工具可以帮助我们从本地管理 Github 仓库，于是我们在使用浏览器时访问的其实是 github 的文件仓库，然后在本地使用 hexo 工具进行网页的管理与博客内容的上传，最终在 github 得到内容的更新，于是不同的内容便展现在网页端。</p>\n",
            "tags": [
                "基础理解"
            ]
        },
        {
            "id": "https://ncufresher.github.io/2024/04/08/hello-world/",
            "url": "https://ncufresher.github.io/2024/04/08/hello-world/",
            "title": "Hello World",
            "date_published": "2024-04-08T03:28:07.767Z",
            "content_html": "<p>Welcome to <span class=\"exturl\" data-url=\"aHR0cHM6Ly9oZXhvLmlvLw==\">Hexo</span>! This is your very first post. Check <span class=\"exturl\" data-url=\"aHR0cHM6Ly9oZXhvLmlvL2RvY3Mv\">documentation</span> for more info. If you get any problems when using Hexo, you can find the answer in <span class=\"exturl\" data-url=\"aHR0cHM6Ly9oZXhvLmlvL2RvY3MvdHJvdWJsZXNob290aW5nLmh0bWw=\">troubleshooting</span> or you can ask me on <span class=\"exturl\" data-url=\"aHR0cHM6Ly9naXRodWIuY29tL2hleG9qcy9oZXhvL2lzc3Vlcw==\">GitHub</span>.</p>\n<h2 id=\"quick-start\"><a class=\"anchor\" href=\"#quick-start\">#</a> Quick Start</h2>\n<h2 id=\"插入图片\"><a class=\"anchor\" href=\"#插入图片\">#</a> 插入图片</h2>\n<h3 id=\"绝对路径引用\"><a class=\"anchor\" href=\"#绝对路径引用\">#</a> 绝对路径引用</h3>\n<p><img data-src=\"https://fuss10.elemecdn.com/e/5d/4a731a90594a4af544c0c25941171jpeg.jpeg\" alt=\"图片\" title=\"绝对引用\" /></p>\n<h3 id=\"相对路径引用\"><a class=\"anchor\" href=\"#相对路径引用\">#</a> 相对路径引用</h3>\n<p><img data-src=\"/images/2.jpg\" alt=\"图片\" title=\"相对引用\" /></p>\n<h3 id=\"create-a-new-post\"><a class=\"anchor\" href=\"#create-a-new-post\">#</a> Create a new post</h3>\n<p><figure class=\"highlight bash\"><table><tr><td class=\"gutter\"><pre><span class=\"line\">1</span><br></pre></td><td class=\"code\"><pre><span class=\"line\">$ hexo new <span class=\"string\">&quot;My New Post&quot;</span></span><br></pre></td></tr></table></figure></p>\n<p>More info: <span class=\"exturl\" data-url=\"aHR0cHM6Ly9oZXhvLmlvL2RvY3Mvd3JpdGluZy5odG1s\">Writing</span></p>\n<h3 id=\"run-server\"><a class=\"anchor\" href=\"#run-server\">#</a> Run server</h3>\n<p><figure class=\"highlight bash\"><table><tr><td class=\"gutter\"><pre><span class=\"line\">1</span><br></pre></td><td class=\"code\"><pre><span class=\"line\">$ hexo server</span><br></pre></td></tr></table></figure></p>\n<p>More info: <span class=\"exturl\" data-url=\"aHR0cHM6Ly9oZXhvLmlvL2RvY3Mvc2VydmVyLmh0bWw=\">Server</span></p>\n<h3 id=\"generate-static-files\"><a class=\"anchor\" href=\"#generate-static-files\">#</a> Generate static files</h3>\n<p><figure class=\"highlight bash\"><table><tr><td class=\"gutter\"><pre><span class=\"line\">1</span><br></pre></td><td class=\"code\"><pre><span class=\"line\">$ hexo generate</span><br></pre></td></tr></table></figure></p>\n<p>More info: <span class=\"exturl\" data-url=\"aHR0cHM6Ly9oZXhvLmlvL2RvY3MvZ2VuZXJhdGluZy5odG1s\">Generating</span></p>\n<h3 id=\"deploy-to-remote-sites\"><a class=\"anchor\" href=\"#deploy-to-remote-sites\">#</a> Deploy to remote sites</h3>\n<p><figure class=\"highlight bash\"><table><tr><td class=\"gutter\"><pre><span class=\"line\">1</span><br></pre></td><td class=\"code\"><pre><span class=\"line\">$ hexo deploy</span><br></pre></td></tr></table></figure></p>\n<p>More info: <span class=\"exturl\" data-url=\"aHR0cHM6Ly9oZXhvLmlvL2RvY3Mvb25lLWNvbW1hbmQtZGVwbG95bWVudC5odG1s\">Deployment</span></p>\n",
            "tags": []
        },
        {
            "id": "https://ncufresher.github.io/2020/12/24/%E6%A8%A1%E6%9D%BF/%E6%A8%A1%E6%9D%BF/",
            "url": "https://ncufresher.github.io/2020/12/24/%E6%A8%A1%E6%9D%BF/%E6%A8%A1%E6%9D%BF/",
            "title": "Markdown使用指南",
            "date_published": "2020-12-24T04:10:45.000Z",
            "content_html": "<h1 id=\"markdownnote\"><a class=\"anchor\" href=\"#markdownnote\">#</a> MarkdownNote</h1>\n<p>common grammar--MarkdownNote</p>\n<p>推荐 markdown 软件<a href=\"%5Bhttps://www.typora.io/\"> Typora</a>](<span class=\"exturl\" data-url=\"aHR0cHM6Ly93d3cudHlwb3JhLmlvLw==\">https://www.typora.io/</span>))<br />\n 后文略...</p>\n",
            "tags": [
                "Markdown使用指南"
            ]
        }
    ]
}